[
    {
        "id": 1,
        "credit": 3
    },
    {
        "id": 2,
        "credit": 3
    },
    {
        "id": 3,
        "credit": 3
    },
    {
        "id": 4,
        "credit": 4
    },
    {
        "id": 5,
        "credit": 2
    },
    {
        "id": 6,
        "credit": 4
    },
    {
        "id": 7,
        "credit": 3
    },
    {
        "id": 8,
        "credit": 4
    },
    {
        "id": 9,
        "credit": 4
    },
    {
        "id": 10,
        "credit": 4
    },
    {
        "id": 11,
        "credit": 4
    },
    {
        "id": 12,
        "credit": 4
    },
    {
        "id": 13,
        "credit": 3
    }
]
